devtools_line_sorter/__init__.py
devtools_line_sorter-1.0.1.dist-info/METADATA
devtools_line_sorter-1.0.1.dist-info/WHEEL
devtools_line_sorter-1.0.1.dist-info/top_level.txt
devtools_line_sorter-1.0.1.dist-info/RECORD
