Metadata-Version: 2.1
Name: devtools-line-sorter
Version: 1.0.1
Summary: Line sorter
Home-page: https://devtools.at/tools/line-sorter
Author: DevTools.at
Author-email: hello@devtools.at
Project-URL: Homepage, https://devtools.at/tools/line-sorter
Project-URL: Repository, https://github.com/devtools-at/line-sorter
Classifier: Development Status :: 4 - Beta
Classifier: Intended Audience :: Developers
Classifier: License :: OSI Approved :: MIT License
Classifier: Programming Language :: Python :: 3
Requires-Python: >=3.8
